[
  {
    "kazanim_kodu": "ARP.5.1.1",
    "kazanim_metni": "DİNLEME/İZLEME-ANLAMLANDIRMA 5.1.1.1.",
    "sinif": 5,
    "okul_turu": "iho",
    "brans_slug": "arapca",
    "ders": "Arapça",
    "unite_no": 1,
    "unite_adi": "MERHABA",
    "kaynak_pdf": "202591213515585-arapca58.pdf",
    "kaynak_sayfa": 14,
    "extraction_yontemi": "regex_tipA",
    "confidence": "high"
  },
  {
    "kazanim_kodu": "ARP.5.1.2",
    "kazanim_metni": "DİL BİLGİSİ SEÇME-KULLANMA",
    "sinif": 5,
    "okul_turu": "iho",
    "brans_slug": "arapca",
    "ders": "Arapça",
    "unite_no": 1,
    "unite_adi": "MERHABA",
    "kaynak_pdf": "202591213515585-arapca58.pdf",
    "kaynak_sayfa": 16,
    "extraction_yontemi": "regex_tipA",
    "confidence": "high"
  },
  {
    "kazanim_kodu": "ARP.5.1.3",
    "kazanim_metni": "SÖZCÜK SEÇME-KULLANMA",
    "sinif": 5,
    "okul_turu": "iho",
    "brans_slug": "arapca",
    "ders": "Arapça",
    "unite_no": 1,
    "unite_adi": "MERHABA",
    "kaynak_pdf": "202591213515585-arapca58.pdf",
    "kaynak_sayfa": 17,
    "extraction_yontemi": "regex_tipA",
    "confidence": "high"
  },
  {
    "kazanim_kodu": "ARP.5.1.4",
    "kazanim_metni": "SESLETİM SEÇME-KULLANMA",
    "sinif": 5,
    "okul_turu": "iho",
    "brans_slug": "arapca",
    "ders": "Arapça",
    "unite_no": 1,
    "unite_adi": "MERHABA",
    "kaynak_pdf": "202591213515585-arapca58.pdf",
    "kaynak_sayfa": 22,
    "extraction_yontemi": "regex_tipA",
    "confidence": "high"
  },
  {
    "kazanim_kodu": "ARP.5.1.5",
    "kazanim_metni": "KONUŞMA-ANLATMA",
    "sinif": 5,
    "okul_turu": "iho",
    "brans_slug": "arapca",
    "ders": "Arapça",
    "unite_no": 1,
    "unite_adi": "MERHABA",
    "kaynak_pdf": "202591213515585-arapca58.pdf",
    "kaynak_sayfa": 17,
    "extraction_yontemi": "regex_tipA",
    "confidence": "high"
  },
  {
    "kazanim_kodu": "ARP.5.1.6",
    "kazanim_metni": "YAZMA-ANLATMA",
    "sinif": 5,
    "okul_turu": "iho",
    "brans_slug": "arapca",
    "ders": "Arapça",
    "unite_no": 1,
    "unite_adi": "MERHABA",
    "kaynak_pdf": "202591213515585-arapca58.pdf",
    "kaynak_sayfa": 18,
    "extraction_yontemi": "regex_tipA",
    "confidence": "high"
  },
  {
    "kazanim_kodu": "ARP.5.2.1",
    "kazanim_metni": "DİNLEME/İZLEME-ANLAMLANDIRMA",
    "sinif": 5,
    "okul_turu": "iho",
    "brans_slug": "arapca",
    "ders": "Arapça",
    "unite_no": 2,
    "unite_adi": "SINIFIM",
    "kaynak_pdf": "202591213515585-arapca58.pdf",
    "kaynak_sayfa": 26,
    "extraction_yontemi": "regex_tipA",
    "confidence": "high"
  },
  {
    "kazanim_kodu": "ARP.5.2.2",
    "kazanim_metni": "DİL BİLGİSİ SEÇME-KULLANMA 9 5.2.2.1.",
    "sinif": 5,
    "okul_turu": "iho",
    "brans_slug": "arapca",
    "ders": "Arapça",
    "unite_no": 2,
    "unite_adi": "SINIFIM",
    "kaynak_pdf": "202591213515585-arapca58.pdf",
    "kaynak_sayfa": 32,
    "extraction_yontemi": "regex_tipA",
    "confidence": "high"
  },
  {
    "kazanim_kodu": "ARP.5.2.3",
    "kazanim_metni": "SÖZCÜK SEÇME-KULLANMA",
    "sinif": 5,
    "okul_turu": "iho",
    "brans_slug": "arapca",
    "ders": "Arapça",
    "unite_no": 2,
    "unite_adi": "SINIFIM",
    "kaynak_pdf": "202591213515585-arapca58.pdf",
    "kaynak_sayfa": 27,
    "extraction_yontemi": "regex_tipA",
    "confidence": "high"
  },
  {
    "kazanim_kodu": "ARP.5.2.4",
    "kazanim_metni": "SESLETİM SEÇME-KULLANMA",
    "sinif": 5,
    "okul_turu": "iho",
    "brans_slug": "arapca",
    "ders": "Arapça",
    "unite_no": 2,
    "unite_adi": "SINIFIM",
    "kaynak_pdf": "202591213515585-arapca58.pdf",
    "kaynak_sayfa": 32,
    "extraction_yontemi": "regex_tipA",
    "confidence": "high"
  },
  {
    "kazanim_kodu": "ARP.5.2.5",
    "kazanim_metni": "KONUŞMA-ANLATMA 8 5.2.5.1.",
    "sinif": 5,
    "okul_turu": "iho",
    "brans_slug": "arapca",
    "ders": "Arapça",
    "unite_no": 2,
    "unite_adi": "SINIFIM",
    "kaynak_pdf": "202591213515585-arapca58.pdf",
    "kaynak_sayfa": 33,
    "extraction_yontemi": "regex_tipA",
    "confidence": "high"
  },
  {
    "kazanim_kodu": "ARP.5.2.6",
    "kazanim_metni": "YAZMA-ANLATMA",
    "sinif": 5,
    "okul_turu": "iho",
    "brans_slug": "arapca",
    "ders": "Arapça",
    "unite_no": 2,
    "unite_adi": "SINIFIM",
    "kaynak_pdf": "202591213515585-arapca58.pdf",
    "kaynak_sayfa": 28,
    "extraction_yontemi": "regex_tipA",
    "confidence": "high"
  },
  {
    "kazanim_kodu": "ARP.5.3.1",
    "kazanim_metni": "DİNLEME/İZLEME-ANLAMLANDIRMA",
    "sinif": 5,
    "okul_turu": "iho",
    "brans_slug": "arapca",
    "ders": "Arapça",
    "unite_no": 3,
    "unite_adi": "AİLEM (يتلََ ئِِاع)",
    "kaynak_pdf": "202591213515585-arapca58.pdf",
    "kaynak_sayfa": 37,
    "extraction_yontemi": "regex_tipA",
    "confidence": "high"
  },
  {
    "kazanim_kodu": "ARP.5.3.2",
    "kazanim_metni": "OKUMA-ANLAMLANDIRMA 1 5.3.2.1.",
    "sinif": 5,
    "okul_turu": "iho",
    "brans_slug": "arapca",
    "ders": "Arapça",
    "unite_no": 3,
    "unite_adi": "AİLEM (يتلََ ئِِاع)",
    "kaynak_pdf": "202591213515585-arapca58.pdf",
    "kaynak_sayfa": 42,
    "extraction_yontemi": "regex_tipA",
    "confidence": "high"
  },
  {
    "kazanim_kodu": "ARP.5.3.24",
    "kazanim_metni": "OKUMA-ANLAMLANDIRMA 5.3.2.18. Aile üyeleri ve mesleklerle ilgili okumaya hazırlık yapabilme",
    "sinif": 5,
    "okul_turu": "iho",
    "brans_slug": "arapca",
    "ders": "Arapça",
    "unite_no": 3,
    "unite_adi": "AİLEM (يتلََ ئِِاع)",
    "kaynak_pdf": "202591213515585-arapca58.pdf",
    "kaynak_sayfa": 37,
    "extraction_yontemi": "regex_tipA",
    "confidence": "high"
  },
  {
    "kazanim_kodu": "ARP.5.3.3",
    "kazanim_metni": "DİL BİLGİSİ SEÇME-KULLANMA",
    "sinif": 5,
    "okul_turu": "iho",
    "brans_slug": "arapca",
    "ders": "Arapça",
    "unite_no": 3,
    "unite_adi": "AİLEM (يتلََ ئِِاع)",
    "kaynak_pdf": "202591213515585-arapca58.pdf",
    "kaynak_sayfa": 38,
    "extraction_yontemi": "regex_tipA",
    "confidence": "high"
  },
  {
    "kazanim_kodu": "ARP.5.3.4",
    "kazanim_metni": "SÖZCÜK SEÇME-KULLANMA 9 5.3.4.1.",
    "sinif": 5,
    "okul_turu": "iho",
    "brans_slug": "arapca",
    "ders": "Arapça",
    "unite_no": 3,
    "unite_adi": "AİLEM (يتلََ ئِِاع)",
    "kaynak_pdf": "202591213515585-arapca58.pdf",
    "kaynak_sayfa": 44,
    "extraction_yontemi": "regex_tipA",
    "confidence": "high"
  },
  {
    "kazanim_kodu": "ARP.5.3.5",
    "kazanim_metni": "KONUŞMA-ANLATMA 9 5.3.5.1. Aile üyeleri ve mesleklerle ilgili konuşmaya hazırlık yapabil8me",
    "sinif": 5,
    "okul_turu": "iho",
    "brans_slug": "arapca",
    "ders": "Arapça",
    "unite_no": 3,
    "unite_adi": "AİLEM (يتلََ ئِِاع)",
    "kaynak_pdf": "202591213515585-arapca58.pdf",
    "kaynak_sayfa": 39,
    "extraction_yontemi": "regex_tipA",
    "confidence": "high"
  },
  {
    "kazanim_kodu": "ARP.5.3.6",
    "kazanim_metni": "YAZMA-ANLATMA 5.3.6.1.",
    "sinif": 5,
    "okul_turu": "iho",
    "brans_slug": "arapca",
    "ders": "Arapça",
    "unite_no": 3,
    "unite_adi": "AİLEM (يتلََ ئِِاع)",
    "kaynak_pdf": "202591213515585-arapca58.pdf",
    "kaynak_sayfa": 45,
    "extraction_yontemi": "regex_tipA",
    "confidence": "high"
  },
  {
    "kazanim_kodu": "ARP.5.4.1",
    "kazanim_metni": "DİNLEME/İZLEME-ANLAMLANDIRMA",
    "sinif": 5,
    "okul_turu": "iho",
    "brans_slug": "arapca",
    "ders": "Arapça",
    "unite_no": 4,
    "unite_adi": "GÜZEL EVİM",
    "kaynak_pdf": "202591213515585-arapca58.pdf",
    "kaynak_sayfa": 48,
    "extraction_yontemi": "regex_tipA",
    "confidence": "high"
  },
  {
    "kazanim_kodu": "ARP.5.4.2",
    "kazanim_metni": "OKUMA-ANLAMLANDIRMA",
    "sinif": 5,
    "okul_turu": "iho",
    "brans_slug": "arapca",
    "ders": "Arapça",
    "unite_no": 4,
    "unite_adi": "GÜZEL EVİM",
    "kaynak_pdf": "202591213515585-arapca58.pdf",
    "kaynak_sayfa": 48,
    "extraction_yontemi": "regex_tipA",
    "confidence": "high"
  },
  {
    "kazanim_kodu": "ARP.5.4.3",
    "kazanim_metni": "DİL BİLGİSİ SEÇME-KULLANMA",
    "sinif": 5,
    "okul_turu": "iho",
    "brans_slug": "arapca",
    "ders": "Arapça",
    "unite_no": 4,
    "unite_adi": "GÜZEL EVİM",
    "kaynak_pdf": "202591213515585-arapca58.pdf",
    "kaynak_sayfa": 49,
    "extraction_yontemi": "regex_tipA",
    "confidence": "high"
  },
  {
    "kazanim_kodu": "ARP.5.4.4",
    "kazanim_metni": "SÖZCÜK SEÇME-KULLANMA 5.4.4.1.",
    "sinif": 5,
    "okul_turu": "iho",
    "brans_slug": "arapca",
    "ders": "Arapça",
    "unite_no": 4,
    "unite_adi": "GÜZEL EVİM",
    "kaynak_pdf": "202591213515585-arapca58.pdf",
    "kaynak_sayfa": 56,
    "extraction_yontemi": "regex_tipA",
    "confidence": "high"
  },
  {
    "kazanim_kodu": "ARP.5.4.5",
    "kazanim_metni": "KONUŞMA-ANLATMA",
    "sinif": 5,
    "okul_turu": "iho",
    "brans_slug": "arapca",
    "ders": "Arapça",
    "unite_no": 4,
    "unite_adi": "GÜZEL EVİM",
    "kaynak_pdf": "202591213515585-arapca58.pdf",
    "kaynak_sayfa": 50,
    "extraction_yontemi": "regex_tipA",
    "confidence": "high"
  },
  {
    "kazanim_kodu": "ARP.5.4.6",
    "kazanim_metni": "YAZMA-ANLATMA 9 5.4.6.1.",
    "sinif": 5,
    "okul_turu": "iho",
    "brans_slug": "arapca",
    "ders": "Arapça",
    "unite_no": 4,
    "unite_adi": "GÜZEL EVİM",
    "kaynak_pdf": "202591213515585-arapca58.pdf",
    "kaynak_sayfa": 58,
    "extraction_yontemi": "regex_tipA",
    "confidence": "high"
  },
  {
    "kazanim_kodu": "ARP.6.1.1",
    "kazanim_metni": "DİNLEME/İZLEME-ANLAMLANDIRMA",
    "sinif": 6,
    "okul_turu": "iho",
    "brans_slug": "arapca",
    "ders": "Arapça",
    "unite_no": 1,
    "unite_adi": "AKRABALARIM",
    "kaynak_pdf": "202591213515585-arapca58.pdf",
    "kaynak_sayfa": 61,
    "extraction_yontemi": "regex_tipA",
    "confidence": "high"
  },
  {
    "kazanim_kodu": "ARP.6.1.2",
    "kazanim_metni": "OKUMA-ANL-AMLANDIRMA 6.1.2.1.",
    "sinif": 6,
    "okul_turu": "iho",
    "brans_slug": "arapca",
    "ders": "Arapça",
    "unite_no": 1,
    "unite_adi": "AKRABALARIM",
    "kaynak_pdf": "202591213515585-arapca58.pdf",
    "kaynak_sayfa": 67,
    "extraction_yontemi": "regex_tipA",
    "confidence": "high"
  },
  {
    "kazanim_kodu": "ARP.6.1.3",
    "kazanim_metni": "DİL BİLGİSİ SEÇM2E-KULLANMA 6.1.3.1.",
    "sinif": 6,
    "okul_turu": "iho",
    "brans_slug": "arapca",
    "ders": "Arapça",
    "unite_no": 1,
    "unite_adi": "AKRABALARIM",
    "kaynak_pdf": "202591213515585-arapca58.pdf",
    "kaynak_sayfa": 68,
    "extraction_yontemi": "regex_tipA",
    "confidence": "high"
  },
  {
    "kazanim_kodu": "ARP.6.1.4",
    "kazanim_metni": "SÖZCÜK SEÇME-KULLANMA 9 6.1.4.1.",
    "sinif": 6,
    "okul_turu": "iho",
    "brans_slug": "arapca",
    "ders": "Arapça",
    "unite_no": 1,
    "unite_adi": "AKRABALARIM",
    "kaynak_pdf": "202591213515585-arapca58.pdf",
    "kaynak_sayfa": 69,
    "extraction_yontemi": "regex_tipA",
    "confidence": "high"
  },
  {
    "kazanim_kodu": "ARP.6.1.5",
    "kazanim_metni": "SESLETİM SEÇ2ME-KULLANMA 6.1.5.1.",
    "sinif": 6,
    "okul_turu": "iho",
    "brans_slug": "arapca",
    "ders": "Arapça",
    "unite_no": 1,
    "unite_adi": "AKRABALARIM",
    "kaynak_pdf": "202591213515585-arapca58.pdf",
    "kaynak_sayfa": 69,
    "extraction_yontemi": "regex_tipA",
    "confidence": "high"
  },
  {
    "kazanim_kodu": "ARP.6.1.6",
    "kazanim_metni": "KONUŞMA-ANLATMA",
    "sinif": 6,
    "okul_turu": "iho",
    "brans_slug": "arapca",
    "ders": "Arapça",
    "unite_no": 1,
    "unite_adi": "AKRABALARIM",
    "kaynak_pdf": "202591213515585-arapca58.pdf",
    "kaynak_sayfa": 63,
    "extraction_yontemi": "regex_tipA",
    "confidence": "high"
  },
  {
    "kazanim_kodu": "ARP.6.1.7",
    "kazanim_metni": "YAZMA-ANLATMA 9 6.1.7.1. Geniş aile bireyleri ve mesleklerle ilgili yazmaya hazırlık yapabil8me",
    "sinif": 6,
    "okul_turu": "iho",
    "brans_slug": "arapca",
    "ders": "Arapça",
    "unite_no": 1,
    "unite_adi": "AKRABALARIM",
    "kaynak_pdf": "202591213515585-arapca58.pdf",
    "kaynak_sayfa": 64,
    "extraction_yontemi": "regex_tipA",
    "confidence": "high"
  },
  {
    "kazanim_kodu": "ARP.6.2.1",
    "kazanim_metni": "DİNLEME/İZLEME-ANLAMLANDIRMA",
    "sinif": 6,
    "okul_turu": "iho",
    "brans_slug": "arapca",
    "ders": "Arapça",
    "unite_no": 2,
    "unite_adi": "HAYDİ OKULA",
    "kaynak_pdf": "202591213515585-arapca58.pdf",
    "kaynak_sayfa": 74,
    "extraction_yontemi": "regex_tipA",
    "confidence": "high"
  },
  {
    "kazanim_kodu": "ARP.6.2.2",
    "kazanim_metni": "OKUMA-ANLAMLANDIRMA 9 6.2.2.1.",
    "sinif": 6,
    "okul_turu": "iho",
    "brans_slug": "arapca",
    "ders": "Arapça",
    "unite_no": 2,
    "unite_adi": "HAYDİ OKULA",
    "kaynak_pdf": "202591213515585-arapca58.pdf",
    "kaynak_sayfa": 81,
    "extraction_yontemi": "regex_tipA",
    "confidence": "high"
  },
  {
    "kazanim_kodu": "ARP.6.2.3",
    "kazanim_metni": "DİL BİLGİSİ SEÇM8E-KULLANMA",
    "sinif": 6,
    "okul_turu": "iho",
    "brans_slug": "arapca",
    "ders": "Arapça",
    "unite_no": 2,
    "unite_adi": "HAYDİ OKULA",
    "kaynak_pdf": "202591213515585-arapca58.pdf",
    "kaynak_sayfa": 75,
    "extraction_yontemi": "regex_tipA",
    "confidence": "high"
  },
  {
    "kazanim_kodu": "ARP.6.2.4",
    "kazanim_metni": "SÖZCÜK SEÇME-KULLANMA 86.2.4.1.",
    "sinif": 6,
    "okul_turu": "iho",
    "brans_slug": "arapca",
    "ders": "Arapça",
    "unite_no": 2,
    "unite_adi": "HAYDİ OKULA",
    "kaynak_pdf": "202591213515585-arapca58.pdf",
    "kaynak_sayfa": 82,
    "extraction_yontemi": "regex_tipA",
    "confidence": "high"
  },
  {
    "kazanim_kodu": "ARP.6.2.5",
    "kazanim_metni": "KONUŞMA-ANLATMA",
    "sinif": 6,
    "okul_turu": "iho",
    "brans_slug": "arapca",
    "ders": "Arapça",
    "unite_no": 2,
    "unite_adi": "HAYDİ OKULA",
    "kaynak_pdf": "202591213515585-arapca58.pdf",
    "kaynak_sayfa": 76,
    "extraction_yontemi": "regex_tipA",
    "confidence": "high"
  },
  {
    "kazanim_kodu": "ARP.6.2.6",
    "kazanim_metni": "YAZMA-ANLA-TMA 6.2.6.1.",
    "sinif": 6,
    "okul_turu": "iho",
    "brans_slug": "arapca",
    "ders": "Arapça",
    "unite_no": 2,
    "unite_adi": "HAYDİ OKULA",
    "kaynak_pdf": "202591213515585-arapca58.pdf",
    "kaynak_sayfa": 84,
    "extraction_yontemi": "regex_tipA",
    "confidence": "high"
  },
  {
    "kazanim_kodu": "ARP.6.3.1",
    "kazanim_metni": "DİNLEME/İZLEME-ANLAMLANDIRMA",
    "sinif": 6,
    "okul_turu": "iho",
    "brans_slug": "arapca",
    "ders": "Arapça",
    "unite_no": 3,
    "unite_adi": "VÜCUDUM (يمسْجِِ )",
    "kaynak_pdf": "202591213515585-arapca58.pdf",
    "kaynak_sayfa": 87,
    "extraction_yontemi": "regex_tipA",
    "confidence": "high"
  },
  {
    "kazanim_kodu": "ARP.6.3.2",
    "kazanim_metni": "OKUMA-ANLAMLANDIRMA 1 6.3.2.1.",
    "sinif": 6,
    "okul_turu": "iho",
    "brans_slug": "arapca",
    "ders": "Arapça",
    "unite_no": 3,
    "unite_adi": "VÜCUDUM (يمسْجِِ )",
    "kaynak_pdf": "202591213515585-arapca58.pdf",
    "kaynak_sayfa": 92,
    "extraction_yontemi": "regex_tipA",
    "confidence": "high"
  },
  {
    "kazanim_kodu": "ARP.6.3.3",
    "kazanim_metni": "DİL BİLGİSİ SEÇME-KULLANMA",
    "sinif": 6,
    "okul_turu": "iho",
    "brans_slug": "arapca",
    "ders": "Arapça",
    "unite_no": 3,
    "unite_adi": "VÜCUDUM (يمسْجِِ )",
    "kaynak_pdf": "202591213515585-arapca58.pdf",
    "kaynak_sayfa": 88,
    "extraction_yontemi": "regex_tipA",
    "confidence": "high"
  },
  {
    "kazanim_kodu": "ARP.6.3.4",
    "kazanim_metni": "SÖZCÜK SEÇME-KULLANMA 9 6.3.4.1.",
    "sinif": 6,
    "okul_turu": "iho",
    "brans_slug": "arapca",
    "ders": "Arapça",
    "unite_no": 3,
    "unite_adi": "VÜCUDUM (يمسْجِِ )",
    "kaynak_pdf": "202591213515585-arapca58.pdf",
    "kaynak_sayfa": 94,
    "extraction_yontemi": "regex_tipA",
    "confidence": "high"
  },
  {
    "kazanim_kodu": "ARP.6.3.5",
    "kazanim_metni": "KONUŞMA-ANLATMA 9 6.3.5.1. Organlar ve duyularla ilgili konuşmaya hazırlık yapabilme",
    "sinif": 6,
    "okul_turu": "iho",
    "brans_slug": "arapca",
    "ders": "Arapça",
    "unite_no": 3,
    "unite_adi": "VÜCUDUM (يمسْجِِ )",
    "kaynak_pdf": "202591213515585-arapca58.pdf",
    "kaynak_sayfa": 89,
    "extraction_yontemi": "regex_tipA",
    "confidence": "high"
  },
  {
    "kazanim_kodu": "ARP.6.3.6",
    "kazanim_metni": "YAZMA-ANLATMA",
    "sinif": 6,
    "okul_turu": "iho",
    "brans_slug": "arapca",
    "ders": "Arapça",
    "unite_no": 3,
    "unite_adi": "VÜCUDUM (يمسْجِِ )",
    "kaynak_pdf": "202591213515585-arapca58.pdf",
    "kaynak_sayfa": 89,
    "extraction_yontemi": "regex_tipA",
    "confidence": "high"
  },
  {
    "kazanim_kodu": "ARP.6.4.1",
    "kazanim_metni": "DİNLEME/İZLEME-ANLAMLANDIRMA",
    "sinif": 6,
    "okul_turu": "iho",
    "brans_slug": "arapca",
    "ders": "Arapça",
    "unite_no": 4,
    "unite_adi": "BU HAFTA HAVA NASIL?",
    "kaynak_pdf": "202591213515585-arapca58.pdf",
    "kaynak_sayfa": 98,
    "extraction_yontemi": "regex_tipA",
    "confidence": "high"
  },
  {
    "kazanim_kodu": "ARP.6.4.2",
    "kazanim_metni": "OKUMA-ANLAMLANDIRMA 6.4.2.1. Hava durumlarıyla ilgili okumaya hazırlık yapabilme",
    "sinif": 6,
    "okul_turu": "iho",
    "brans_slug": "arapca",
    "ders": "Arapça",
    "unite_no": 4,
    "unite_adi": "BU HAFTA HAVA NASIL?",
    "kaynak_pdf": "202591213515585-arapca58.pdf",
    "kaynak_sayfa": 98,
    "extraction_yontemi": "regex_tipA",
    "confidence": "high"
  },
  {
    "kazanim_kodu": "ARP.6.4.3",
    "kazanim_metni": "DİL BİLGİSİ SEÇME-KULLANMA",
    "sinif": 6,
    "okul_turu": "iho",
    "brans_slug": "arapca",
    "ders": "Arapça",
    "unite_no": 4,
    "unite_adi": "BU HAFTA HAVA NASIL?",
    "kaynak_pdf": "202591213515585-arapca58.pdf",
    "kaynak_sayfa": 106,
    "extraction_yontemi": "regex_tipA",
    "confidence": "high"
  },
  {
    "kazanim_kodu": "ARP.6.4.34",
    "kazanim_metni": "DİL BİLGİSİ SEÇME-KULLANMA",
    "sinif": 6,
    "okul_turu": "iho",
    "brans_slug": "arapca",
    "ders": "Arapça",
    "unite_no": 4,
    "unite_adi": "BU HAFTA HAVA NASIL?",
    "kaynak_pdf": "202591213515585-arapca58.pdf",
    "kaynak_sayfa": 99,
    "extraction_yontemi": "regex_tipA",
    "confidence": "high"
  },
  {
    "kazanim_kodu": "ARP.6.4.4",
    "kazanim_metni": "SÖZCÜK SEÇME-KULLANMA 9 6.4.4.1.",
    "sinif": 6,
    "okul_turu": "iho",
    "brans_slug": "arapca",
    "ders": "Arapça",
    "unite_no": 4,
    "unite_adi": "BU HAFTA HAVA NASIL?",
    "kaynak_pdf": "202591213515585-arapca58.pdf",
    "kaynak_sayfa": 107,
    "extraction_yontemi": "regex_tipA",
    "confidence": "high"
  },
  {
    "kazanim_kodu": "ARP.6.4.5",
    "kazanim_metni": "KONUŞMA-ANL2ATMA 6.4.5.1.",
    "sinif": 6,
    "okul_turu": "iho",
    "brans_slug": "arapca",
    "ders": "Arapça",
    "unite_no": 4,
    "unite_adi": "BU HAFTA HAVA NASIL?",
    "kaynak_pdf": "202591213515585-arapca58.pdf",
    "kaynak_sayfa": 107,
    "extraction_yontemi": "regex_tipA",
    "confidence": "high"
  },
  {
    "kazanim_kodu": "ARP.6.4.6",
    "kazanim_metni": "YAZMA-ANLATMA 26.4.6.1.",
    "sinif": 6,
    "okul_turu": "iho",
    "brans_slug": "arapca",
    "ders": "Arapça",
    "unite_no": 4,
    "unite_adi": "BU HAFTA HAVA NASIL?",
    "kaynak_pdf": "202591213515585-arapca58.pdf",
    "kaynak_sayfa": 108,
    "extraction_yontemi": "regex_tipA",
    "confidence": "high"
  },
  {
    "kazanim_kodu": "ARP.7.1.1",
    "kazanim_metni": "DİNLEME/İZLEME-ANLAMLANDIRMA Uygulamaları 7.1.1.1.",
    "sinif": 7,
    "okul_turu": "iho",
    "brans_slug": "arapca",
    "ders": "Arapça",
    "unite_no": 1,
    "unite_adi": "BUGÜN NE YAPTIM?",
    "kaynak_pdf": "202591213515585-arapca58.pdf",
    "kaynak_sayfa": 117,
    "extraction_yontemi": "regex_tipA",
    "confidence": "high"
  },
  {
    "kazanim_kodu": "ARP.7.1.2",
    "kazanim_metni": "OKUMA-ANLAMLANDIRMA 8 7.1.2.1.",
    "sinif": 7,
    "okul_turu": "iho",
    "brans_slug": "arapca",
    "ders": "Arapça",
    "unite_no": 1,
    "unite_adi": "BUGÜN NE YAPTIM?",
    "kaynak_pdf": "202591213515585-arapca58.pdf",
    "kaynak_sayfa": 117,
    "extraction_yontemi": "regex_tipA",
    "confidence": "high"
  },
  {
    "kazanim_kodu": "ARP.7.1.3",
    "kazanim_metni": "DİL BİLGİSİ SEÇME-KULLANMA 8",
    "sinif": 7,
    "okul_turu": "iho",
    "brans_slug": "arapca",
    "ders": "Arapça",
    "unite_no": 1,
    "unite_adi": "BUGÜN NE YAPTIM?",
    "kaynak_pdf": "202591213515585-arapca58.pdf",
    "kaynak_sayfa": 112,
    "extraction_yontemi": "regex_tipA",
    "confidence": "high"
  },
  {
    "kazanim_kodu": "ARP.7.1.4",
    "kazanim_metni": "SÖZCÜK SEÇME-KULLANMA",
    "sinif": 7,
    "okul_turu": "iho",
    "brans_slug": "arapca",
    "ders": "Arapça",
    "unite_no": 1,
    "unite_adi": "BUGÜN NE YAPTIM?",
    "kaynak_pdf": "202591213515585-arapca58.pdf",
    "kaynak_sayfa": 112,
    "extraction_yontemi": "regex_tipA",
    "confidence": "high"
  },
  {
    "kazanim_kodu": "ARP.7.1.5",
    "kazanim_metni": "KONUŞMA-ANLATMA 4 7.1.5.1. Günlük hayatla ilgili konuşmaya hazırl8ık yapabilme",
    "sinif": 7,
    "okul_turu": "iho",
    "brans_slug": "arapca",
    "ders": "Arapça",
    "unite_no": 1,
    "unite_adi": "BUGÜN NE YAPTIM?",
    "kaynak_pdf": "202591213515585-arapca58.pdf",
    "kaynak_sayfa": 113,
    "extraction_yontemi": "regex_tipA",
    "confidence": "high"
  },
  {
    "kazanim_kodu": "ARP.7.1.6",
    "kazanim_metni": "YAZMA-ANLATMA 9 7.1.6.1. Günlük hayatla ilgili yazmaya hazırlık yapabilme",
    "sinif": 7,
    "okul_turu": "iho",
    "brans_slug": "arapca",
    "ders": "Arapça",
    "unite_no": 1,
    "unite_adi": "BUGÜN NE YAPTIM?",
    "kaynak_pdf": "202591213515585-arapca58.pdf",
    "kaynak_sayfa": 114,
    "extraction_yontemi": "regex_tipA",
    "confidence": "high"
  },
  {
    "kazanim_kodu": "ARP.7.2.1",
    "kazanim_metni": "DİNLEME/İZLEME-ANLAMLANDIRMA",
    "sinif": 7,
    "okul_turu": "iho",
    "brans_slug": "arapca",
    "ders": "Arapça",
    "unite_no": 2,
    "unite_adi": "ALIŞVERİŞ ZAMANI",
    "kaynak_pdf": "202591213515585-arapca58.pdf",
    "kaynak_sayfa": 123,
    "extraction_yontemi": "regex_tipA",
    "confidence": "high"
  },
  {
    "kazanim_kodu": "ARP.7.2.2",
    "kazanim_metni": "OKUMA-ANLAMLANDIRMA 8 7.2.2.1.",
    "sinif": 7,
    "okul_turu": "iho",
    "brans_slug": "arapca",
    "ders": "Arapça",
    "unite_no": 2,
    "unite_adi": "ALIŞVERİŞ ZAMANI",
    "kaynak_pdf": "202591213515585-arapca58.pdf",
    "kaynak_sayfa": 129,
    "extraction_yontemi": "regex_tipA",
    "confidence": "high"
  },
  {
    "kazanim_kodu": "ARP.7.2.3",
    "kazanim_metni": "DİL BİLGİSİ SEÇME-KULLANMA",
    "sinif": 7,
    "okul_turu": "iho",
    "brans_slug": "arapca",
    "ders": "Arapça",
    "unite_no": 2,
    "unite_adi": "ALIŞVERİŞ ZAMANI",
    "kaynak_pdf": "202591213515585-arapca58.pdf",
    "kaynak_sayfa": 124,
    "extraction_yontemi": "regex_tipA",
    "confidence": "high"
  },
  {
    "kazanim_kodu": "ARP.7.2.4",
    "kazanim_metni": "SÖZCÜK SEÇME-KULLANMA 9 7.2.4.1.",
    "sinif": 7,
    "okul_turu": "iho",
    "brans_slug": "arapca",
    "ders": "Arapça",
    "unite_no": 2,
    "unite_adi": "ALIŞVERİŞ ZAMANI",
    "kaynak_pdf": "202591213515585-arapca58.pdf",
    "kaynak_sayfa": 131,
    "extraction_yontemi": "regex_tipA",
    "confidence": "high"
  },
  {
    "kazanim_kodu": "ARP.7.2.5",
    "kazanim_metni": "KONUŞMA-ANLATMA",
    "sinif": 7,
    "okul_turu": "iho",
    "brans_slug": "arapca",
    "ders": "Arapça",
    "unite_no": 2,
    "unite_adi": "ALIŞVERİŞ ZAMANI",
    "kaynak_pdf": "202591213515585-arapca58.pdf",
    "kaynak_sayfa": 125,
    "extraction_yontemi": "regex_tipA",
    "confidence": "high"
  },
  {
    "kazanim_kodu": "ARP.7.2.6",
    "kazanim_metni": "YAZMA-ANLATMA",
    "sinif": 7,
    "okul_turu": "iho",
    "brans_slug": "arapca",
    "ders": "Arapça",
    "unite_no": 2,
    "unite_adi": "ALIŞVERİŞ ZAMANI",
    "kaynak_pdf": "202591213515585-arapca58.pdf",
    "kaynak_sayfa": 126,
    "extraction_yontemi": "regex_tipA",
    "confidence": "high"
  },
  {
    "kazanim_kodu": "ARP.7.3.1",
    "kazanim_metni": "DİNLEME/İZLEME-ANLAMLANDIRMA",
    "sinif": 7,
    "okul_turu": "iho",
    "brans_slug": "arapca",
    "ders": "Arapça",
    "unite_no": 3,
    "unite_adi": "NEREYE SEYAHAT EDELİM? (؟رْ",
    "kaynak_pdf": "202591213515585-arapca58.pdf",
    "kaynak_sayfa": 135,
    "extraction_yontemi": "regex_tipA",
    "confidence": "high"
  },
  {
    "kazanim_kodu": "ARP.7.3.2",
    "kazanim_metni": "OKUMA-ANLAMLANDIRMA",
    "sinif": 7,
    "okul_turu": "iho",
    "brans_slug": "arapca",
    "ders": "Arapça",
    "unite_no": 3,
    "unite_adi": "NEREYE SEYAHAT EDELİM? (؟رْ",
    "kaynak_pdf": "202591213515585-arapca58.pdf",
    "kaynak_sayfa": 135,
    "extraction_yontemi": "regex_tipA",
    "confidence": "high"
  },
  {
    "kazanim_kodu": "ARP.7.3.3",
    "kazanim_metni": "DİL BİLGİSİ SEÇME-KULLANMA 7.3.3.1.",
    "sinif": 7,
    "okul_turu": "iho",
    "brans_slug": "arapca",
    "ders": "Arapça",
    "unite_no": 3,
    "unite_adi": "NEREYE SEYAHAT EDELİM? (؟رْ",
    "kaynak_pdf": "202591213515585-arapca58.pdf",
    "kaynak_sayfa": 141,
    "extraction_yontemi": "regex_tipA",
    "confidence": "high"
  },
  {
    "kazanim_kodu": "ARP.7.3.4",
    "kazanim_metni": "SÖZCÜK SEÇME-KULLANMA 9 7.3.4.1.",
    "sinif": 7,
    "okul_turu": "iho",
    "brans_slug": "arapca",
    "ders": "Arapça",
    "unite_no": 3,
    "unite_adi": "NEREYE SEYAHAT EDELİM? (؟رْ",
    "kaynak_pdf": "202591213515585-arapca58.pdf",
    "kaynak_sayfa": 142,
    "extraction_yontemi": "regex_tipA",
    "confidence": "high"
  },
  {
    "kazanim_kodu": "ARP.7.3.5",
    "kazanim_metni": "KONUŞMA-ANLATMA 9 7.3.5.1. Ulaşımla ilgili konuşmaya hazırlık yapabilme",
    "sinif": 7,
    "okul_turu": "iho",
    "brans_slug": "arapca",
    "ders": "Arapça",
    "unite_no": 3,
    "unite_adi": "NEREYE SEYAHAT EDELİM? (؟رْ",
    "kaynak_pdf": "202591213515585-arapca58.pdf",
    "kaynak_sayfa": 137,
    "extraction_yontemi": "regex_tipA",
    "confidence": "high"
  },
  {
    "kazanim_kodu": "ARP.7.3.6",
    "kazanim_metni": "YAZMA-ANLATMA",
    "sinif": 7,
    "okul_turu": "iho",
    "brans_slug": "arapca",
    "ders": "Arapça",
    "unite_no": 3,
    "unite_adi": "NEREYE SEYAHAT EDELİM? (؟رْ",
    "kaynak_pdf": "202591213515585-arapca58.pdf",
    "kaynak_sayfa": 137,
    "extraction_yontemi": "regex_tipA",
    "confidence": "high"
  },
  {
    "kazanim_kodu": "ARP.7.4.1",
    "kazanim_metni": "DİNLEME/İZLEME-ANLAMLANDIRMA",
    "sinif": 7,
    "okul_turu": "iho",
    "brans_slug": "arapca",
    "ders": "Arapça",
    "unite_no": 4,
    "unite_adi": "ŞEHRİM VE ÜLKEM",
    "kaynak_pdf": "202591213515585-arapca58.pdf",
    "kaynak_sayfa": 146,
    "extraction_yontemi": "regex_tipA",
    "confidence": "high"
  },
  {
    "kazanim_kodu": "ARP.7.4.2",
    "kazanim_metni": "OKUMA-ANLAMLANDIRMA 87.4.2.1. Şehir ve ülkeyle ilgili okumaya hazırlık yapabilme",
    "sinif": 7,
    "okul_turu": "iho",
    "brans_slug": "arapca",
    "ders": "Arapça",
    "unite_no": 4,
    "unite_adi": "ŞEHRİM VE ÜLKEM",
    "kaynak_pdf": "202591213515585-arapca58.pdf",
    "kaynak_sayfa": 146,
    "extraction_yontemi": "regex_tipA",
    "confidence": "high"
  },
  {
    "kazanim_kodu": "ARP.7.4.3",
    "kazanim_metni": "DİL BİLGİSİ SEÇME-KULLANMA 7.4.3.1.",
    "sinif": 7,
    "okul_turu": "iho",
    "brans_slug": "arapca",
    "ders": "Arapça",
    "unite_no": 4,
    "unite_adi": "ŞEHRİM VE ÜLKEM",
    "kaynak_pdf": "202591213515585-arapca58.pdf",
    "kaynak_sayfa": 153,
    "extraction_yontemi": "regex_tipA",
    "confidence": "high"
  },
  {
    "kazanim_kodu": "ARP.7.4.4",
    "kazanim_metni": "SÖZCÜK SEÇME-KULLANMA 7.4.4.1. 1 7.4.4.1.",
    "sinif": 7,
    "okul_turu": "iho",
    "brans_slug": "arapca",
    "ders": "Arapça",
    "unite_no": 4,
    "unite_adi": "ŞEHRİM VE ÜLKEM",
    "kaynak_pdf": "202591213515585-arapca58.pdf",
    "kaynak_sayfa": 154,
    "extraction_yontemi": "regex_tipA",
    "confidence": "high"
  },
  {
    "kazanim_kodu": "ARP.7.4.5",
    "kazanim_metni": "KONUŞMA-A NLATMA",
    "sinif": 7,
    "okul_turu": "iho",
    "brans_slug": "arapca",
    "ders": "Arapça",
    "unite_no": 4,
    "unite_adi": "ŞEHRİM VE ÜLKEM",
    "kaynak_pdf": "202591213515585-arapca58.pdf",
    "kaynak_sayfa": 154,
    "extraction_yontemi": "regex_tipA",
    "confidence": "high"
  },
  {
    "kazanim_kodu": "ARP.7.4.6",
    "kazanim_metni": "YAZMA-ANLATMA",
    "sinif": 7,
    "okul_turu": "iho",
    "brans_slug": "arapca",
    "ders": "Arapça",
    "unite_no": 4,
    "unite_adi": "ŞEHRİM VE ÜLKEM",
    "kaynak_pdf": "202591213515585-arapca58.pdf",
    "kaynak_sayfa": 149,
    "extraction_yontemi": "regex_tipA",
    "confidence": "high"
  },
  {
    "kazanim_kodu": "ARP.8.1.1",
    "kazanim_metni": "DİNLEME/İZLEME-ANLAMLANDIRMA",
    "sinif": 8,
    "okul_turu": "iho",
    "brans_slug": "arapca",
    "ders": "Arapça",
    "unite_no": 1,
    "unite_adi": "MERHABA",
    "kaynak_pdf": "202591213515585-arapca58.pdf",
    "kaynak_sayfa": 158,
    "extraction_yontemi": "regex_tipA",
    "confidence": "high"
  },
  {
    "kazanim_kodu": "ARP.8.1.2",
    "kazanim_metni": "OKUMA-ANLAMLANDIRMA 8.1.2.1.",
    "sinif": 8,
    "okul_turu": "iho",
    "brans_slug": "arapca",
    "ders": "Arapça",
    "unite_no": 1,
    "unite_adi": "MERHABA",
    "kaynak_pdf": "202591213515585-arapca58.pdf",
    "kaynak_sayfa": 163,
    "extraction_yontemi": "regex_tipA",
    "confidence": "high"
  },
  {
    "kazanim_kodu": "ARP.8.1.3",
    "kazanim_metni": "DİL BİLGİSİ SEÇME-KULLANMA 8.1.3.1.",
    "sinif": 8,
    "okul_turu": "iho",
    "brans_slug": "arapca",
    "ders": "Arapça",
    "unite_no": 1,
    "unite_adi": "MERHABA",
    "kaynak_pdf": "202591213515585-arapca58.pdf",
    "kaynak_sayfa": 164,
    "extraction_yontemi": "regex_tipA",
    "confidence": "high"
  },
  {
    "kazanim_kodu": "ARP.8.1.4",
    "kazanim_metni": "SÖ6ZCÜK SEÇME-KULLANMA",
    "sinif": 8,
    "okul_turu": "iho",
    "brans_slug": "arapca",
    "ders": "Arapça",
    "unite_no": 1,
    "unite_adi": "MERHABA",
    "kaynak_pdf": "202591213515585-arapca58.pdf",
    "kaynak_sayfa": 159,
    "extraction_yontemi": "regex_tipA",
    "confidence": "high"
  },
  {
    "kazanim_kodu": "ARP.8.1.5",
    "kazanim_metni": "KONUŞMA-ANLATMA 9 8.1.5.1. Günlük etkinliklerle ilgili konuşmaya hazırlık yapabilme",
    "sinif": 8,
    "okul_turu": "iho",
    "brans_slug": "arapca",
    "ders": "Arapça",
    "unite_no": 1,
    "unite_adi": "MERHABA",
    "kaynak_pdf": "202591213515585-arapca58.pdf",
    "kaynak_sayfa": 160,
    "extraction_yontemi": "regex_tipA",
    "confidence": "high"
  },
  {
    "kazanim_kodu": "ARP.8.1.6",
    "kazanim_metni": "YAZMA-ANLATMA 98.1.6.1. Günlük etkinliklerle ilgili yazmaya hazırlık yapabilme",
    "sinif": 8,
    "okul_turu": "iho",
    "brans_slug": "arapca",
    "ders": "Arapça",
    "unite_no": 1,
    "unite_adi": "MERHABA",
    "kaynak_pdf": "202591213515585-arapca58.pdf",
    "kaynak_sayfa": 160,
    "extraction_yontemi": "regex_tipA",
    "confidence": "high"
  },
  {
    "kazanim_kodu": "ARP.8.2.1",
    "kazanim_metni": "DİNLEME/İZLEME-ANLAMLANDIRMA",
    "sinif": 8,
    "okul_turu": "iho",
    "brans_slug": "arapca",
    "ders": "Arapça",
    "unite_no": 2,
    "unite_adi": "SAĞLIKLI HAYATIM (ةيَحِِّ صِِّ لا يتايَحَ)",
    "kaynak_pdf": "202591213515585-arapca58.pdf",
    "kaynak_sayfa": 169,
    "extraction_yontemi": "regex_tipA",
    "confidence": "high"
  },
  {
    "kazanim_kodu": "ARP.8.2.2",
    "kazanim_metni": "OKUMA-ANLAMLANDIRMA 1 8.2.2.1.",
    "sinif": 8,
    "okul_turu": "iho",
    "brans_slug": "arapca",
    "ders": "Arapça",
    "unite_no": 2,
    "unite_adi": "SAĞLIKLI HAYATIM (ةيَحِِّ صِِّ لا يتايَحَ)",
    "kaynak_pdf": "202591213515585-arapca58.pdf",
    "kaynak_sayfa": 175,
    "extraction_yontemi": "regex_tipA",
    "confidence": "high"
  },
  {
    "kazanim_kodu": "ARP.8.2.3",
    "kazanim_metni": "DİL BİLGİSİ SEÇME-KULLANMA 98.2.3.1.",
    "sinif": 8,
    "okul_turu": "iho",
    "brans_slug": "arapca",
    "ders": "Arapça",
    "unite_no": 2,
    "unite_adi": "SAĞLIKLI HAYATIM (ةيَحِِّ صِِّ لا يتايَحَ)",
    "kaynak_pdf": "202591213515585-arapca58.pdf",
    "kaynak_sayfa": 176,
    "extraction_yontemi": "regex_tipA",
    "confidence": "high"
  },
  {
    "kazanim_kodu": "ARP.8.2.4",
    "kazanim_metni": "SÖZCÜK SEÇME-KULLANMA 8.2.4.1.",
    "sinif": 8,
    "okul_turu": "iho",
    "brans_slug": "arapca",
    "ders": "Arapça",
    "unite_no": 2,
    "unite_adi": "SAĞLIKLI HAYATIM (ةيَحِِّ صِِّ لا يتايَحَ)",
    "kaynak_pdf": "202591213515585-arapca58.pdf",
    "kaynak_sayfa": 177,
    "extraction_yontemi": "regex_tipA",
    "confidence": "high"
  },
  {
    "kazanim_kodu": "ARP.8.2.5",
    "kazanim_metni": "KONUŞMA-ANLATMA 8.2.5.1.",
    "sinif": 8,
    "okul_turu": "iho",
    "brans_slug": "arapca",
    "ders": "Arapça",
    "unite_no": 2,
    "unite_adi": "SAĞLIKLI HAYATIM (ةيَحِِّ صِِّ لا يتايَحَ)",
    "kaynak_pdf": "202591213515585-arapca58.pdf",
    "kaynak_sayfa": 177,
    "extraction_yontemi": "regex_tipA",
    "confidence": "high"
  },
  {
    "kazanim_kodu": "ARP.8.2.6",
    "kazanim_metni": "YAZMA-ANLATMA 8.2.6.14.",
    "sinif": 8,
    "okul_turu": "iho",
    "brans_slug": "arapca",
    "ders": "Arapça",
    "unite_no": 2,
    "unite_adi": "SAĞLIKLI HAYATIM (ةيَحِِّ صِِّ لا يتايَحَ)",
    "kaynak_pdf": "202591213515585-arapca58.pdf",
    "kaynak_sayfa": 178,
    "extraction_yontemi": "regex_tipA",
    "confidence": "high"
  },
  {
    "kazanim_kodu": "ARP.8.3.1",
    "kazanim_metni": "DİNLEME/İZLEME-ANLAMLANDIRMA",
    "sinif": 8,
    "okul_turu": "iho",
    "brans_slug": "arapca",
    "ders": "Arapça",
    "unite_no": 3,
    "unite_adi": "İLETİŞİM GÜNLÜĞÜM (ةيْ",
    "kaynak_pdf": "202591213515585-arapca58.pdf",
    "kaynak_sayfa": 181,
    "extraction_yontemi": "regex_tipA",
    "confidence": "high"
  },
  {
    "kazanim_kodu": "ARP.8.3.2",
    "kazanim_metni": "OKUMA-ANLAMLANDIRMA",
    "sinif": 8,
    "okul_turu": "iho",
    "brans_slug": "arapca",
    "ders": "Arapça",
    "unite_no": 3,
    "unite_adi": "İLETİŞİM GÜNLÜĞÜM (ةيْ",
    "kaynak_pdf": "202591213515585-arapca58.pdf",
    "kaynak_sayfa": 181,
    "extraction_yontemi": "regex_tipA",
    "confidence": "high"
  },
  {
    "kazanim_kodu": "ARP.8.3.3",
    "kazanim_metni": "DİL BİLGİSİ SEÇME-KULLANMA 8.3.3.1.",
    "sinif": 8,
    "okul_turu": "iho",
    "brans_slug": "arapca",
    "ders": "Arapça",
    "unite_no": 3,
    "unite_adi": "İLETİŞİM GÜNLÜĞÜM (ةيْ",
    "kaynak_pdf": "202591213515585-arapca58.pdf",
    "kaynak_sayfa": 187,
    "extraction_yontemi": "regex_tipA",
    "confidence": "high"
  },
  {
    "kazanim_kodu": "ARP.8.3.4",
    "kazanim_metni": "SÖZCÜK SEÇME-KULLANMA 9 8.3.4.1.",
    "sinif": 8,
    "okul_turu": "iho",
    "brans_slug": "arapca",
    "ders": "Arapça",
    "unite_no": 3,
    "unite_adi": "İLETİŞİM GÜNLÜĞÜM (ةيْ",
    "kaynak_pdf": "202591213515585-arapca58.pdf",
    "kaynak_sayfa": 188,
    "extraction_yontemi": "regex_tipA",
    "confidence": "high"
  },
  {
    "kazanim_kodu": "ARP.8.3.5",
    "kazanim_metni": "KONUŞMA-ANLATMA 9 8.3.5.1. İletişimle ilgili konuşmaya hazırlık yapabilme",
    "sinif": 8,
    "okul_turu": "iho",
    "brans_slug": "arapca",
    "ders": "Arapça",
    "unite_no": 3,
    "unite_adi": "İLETİŞİM GÜNLÜĞÜM (ةيْ",
    "kaynak_pdf": "202591213515585-arapca58.pdf",
    "kaynak_sayfa": 183,
    "extraction_yontemi": "regex_tipA",
    "confidence": "high"
  },
  {
    "kazanim_kodu": "ARP.8.3.6",
    "kazanim_metni": "YAZMA-ANLATMA 8.3.6.1.",
    "sinif": 8,
    "okul_turu": "iho",
    "brans_slug": "arapca",
    "ders": "Arapça",
    "unite_no": 3,
    "unite_adi": "İLETİŞİM GÜNLÜĞÜM (ةيْ",
    "kaynak_pdf": "202591213515585-arapca58.pdf",
    "kaynak_sayfa": 189,
    "extraction_yontemi": "regex_tipA",
    "confidence": "high"
  },
  {
    "kazanim_kodu": "ARP.8.4.1",
    "kazanim_metni": "DİNLEME/İZLEME-ANLAMLANDIRMA",
    "sinif": 8,
    "okul_turu": "iho",
    "brans_slug": "arapca",
    "ders": "Arapça",
    "unite_no": 4,
    "unite_adi": "MEZUN OLUYORUM",
    "kaynak_pdf": "202591213515585-arapca58.pdf",
    "kaynak_sayfa": 192,
    "extraction_yontemi": "regex_tipA",
    "confidence": "high"
  },
  {
    "kazanim_kodu": "ARP.8.4.2",
    "kazanim_metni": "OKUMA-A1NLAMLANDIRMA 8.4.2.1.",
    "sinif": 8,
    "okul_turu": "iho",
    "brans_slug": "arapca",
    "ders": "Arapça",
    "unite_no": 4,
    "unite_adi": "MEZUN OLUYORUM",
    "kaynak_pdf": "202591213515585-arapca58.pdf",
    "kaynak_sayfa": 198,
    "extraction_yontemi": "regex_tipA",
    "confidence": "high"
  },
  {
    "kazanim_kodu": "ARP.8.4.3",
    "kazanim_metni": "DİL BİLGİSİ SEÇME-KULLANMA",
    "sinif": 8,
    "okul_turu": "iho",
    "brans_slug": "arapca",
    "ders": "Arapça",
    "unite_no": 4,
    "unite_adi": "MEZUN OLUYORUM",
    "kaynak_pdf": "202591213515585-arapca58.pdf",
    "kaynak_sayfa": 193,
    "extraction_yontemi": "regex_tipA",
    "confidence": "high"
  },
  {
    "kazanim_kodu": "ARP.8.4.4",
    "kazanim_metni": "SÖZCÜK SEÇME-KULLANMA",
    "sinif": 8,
    "okul_turu": "iho",
    "brans_slug": "arapca",
    "ders": "Arapça",
    "unite_no": 4,
    "unite_adi": "MEZUN OLUYORUM",
    "kaynak_pdf": "202591213515585-arapca58.pdf",
    "kaynak_sayfa": 194,
    "extraction_yontemi": "regex_tipA",
    "confidence": "high"
  },
  {
    "kazanim_kodu": "ARP.8.4.5",
    "kazanim_metni": "KONUŞMA-ANLATMA 9 8.4.5.1.",
    "sinif": 8,
    "okul_turu": "iho",
    "brans_slug": "arapca",
    "ders": "Arapça",
    "unite_no": 4,
    "unite_adi": "MEZUN OLUYORUM",
    "kaynak_pdf": "202591213515585-arapca58.pdf",
    "kaynak_sayfa": 200,
    "extraction_yontemi": "regex_tipA",
    "confidence": "high"
  },
  {
    "kazanim_kodu": "ARP.8.4.6",
    "kazanim_metni": "YAZMA-ANLATMA 8.4.6.1.",
    "sinif": 8,
    "okul_turu": "iho",
    "brans_slug": "arapca",
    "ders": "Arapça",
    "unite_no": 4,
    "unite_adi": "MEZUN OLUYORUM",
    "kaynak_pdf": "202591213515585-arapca58.pdf",
    "kaynak_sayfa": 201,
    "extraction_yontemi": "regex_tipA",
    "confidence": "high"
  }
]