[
  {
    "kod": "HMU.11.1.1",
    "ad": ". öğrenciye kazandırılması VE SÜREÇ BİLEŞENLERİ HMU.11.1.1. Ülkemizdeki din hiz- Öğrenme çıktı",
    "sinif": 11,
    "ders": "Hitabet ve Mesleki Uygulama",
    "brans_slug": "ihl_meslek_dersleri",
    "kaynak_pdf": "2026512154649995-hitabetmeslekdöp.pdf",
    "kaynak_sayfa": 13
  },
  {
    "kod": "HMU.11.1.2",
    "ad": ". Din hizmetlerinde iletişim ve hitabetin unsurlarını çözümleyebilme",
    "sinif": 11,
    "ders": "Hitabet ve Mesleki Uygulama",
    "brans_slug": "ihl_meslek_dersleri",
    "kaynak_pdf": "2026512154649995-hitabetmeslekdöp.pdf",
    "kaynak_sayfa": 15
  },
  {
    "kod": "HMU.11.2.1",
    "ad": ". Vaazı usulüne uygun olarak yerine getirebilme",
    "sinif": 11,
    "ders": "Hitabet ve Mesleki Uygulama",
    "brans_slug": "ihl_meslek_dersleri",
    "kaynak_pdf": "2026512154649995-hitabetmeslekdöp.pdf",
    "kaynak_sayfa": 19
  },
  {
    "kod": "HMU.11.2.2",
    "ad": ". Hutbeyi usulüne uygun olarak yerine getirebilme",
    "sinif": 11,
    "ders": "Hitabet ve Mesleki Uygulama",
    "brans_slug": "ihl_meslek_dersleri",
    "kaynak_pdf": "2026512154649995-hitabetmeslekdöp.pdf",
    "kaynak_sayfa": 19
  },
  {
    "kod": "HMU.11.2.3",
    "ad": ". 4–6 yaş grubuna yönelik din eğitimini usulüne uygun olarak yerine getirebilme",
    "sinif": 11,
    "ders": "Hitabet ve Mesleki Uygulama",
    "brans_slug": "ihl_meslek_dersleri",
    "kaynak_pdf": "2026512154649995-hitabetmeslekdöp.pdf",
    "kaynak_sayfa": 19
  },
  {
    "kod": "HMU.11.3.1",
    "ad": ". Cami musikisi örneklerini usulüne uygun biçimde yerine getirebilme",
    "sinif": 11,
    "ders": "Hitabet ve Mesleki Uygulama",
    "brans_slug": "ihl_meslek_dersleri",
    "kaynak_pdf": "2026512154649995-hitabetmeslekdöp.pdf",
    "kaynak_sayfa": 24
  },
  {
    "kod": "HMU.11.3.2",
    "ad": ". Dua örneklerini usulüne uygun biçimde yerine getirebilme",
    "sinif": 11,
    "ders": "Hitabet ve Mesleki Uygulama",
    "brans_slug": "ihl_meslek_dersleri",
    "kaynak_pdf": "2026512154649995-hitabetmeslekdöp.pdf",
    "kaynak_sayfa": 24
  },
  {
    "kod": "HMU.11.4.1",
    "ad": ". Sosyal yaşamda yer alan dinî merasimleri usulüne uygun biçimde yerine",
    "sinif": 11,
    "ders": "Hitabet ve Mesleki Uygulama",
    "brans_slug": "ihl_meslek_dersleri",
    "kaynak_pdf": "2026512154649995-hitabetmeslekdöp.pdf",
    "kaynak_sayfa": 28
  },
  {
    "kod": "HMU.11.4.2",
    "ad": ". Cenazeyle ilgili dinî işlemleri usulüne uygun biçimde yerine getirebilme",
    "sinif": 11,
    "ders": "Hitabet ve Mesleki Uygulama",
    "brans_slug": "ihl_meslek_dersleri",
    "kaynak_pdf": "2026512154649995-hitabetmeslekdöp.pdf",
    "kaynak_sayfa": 28
  }
]