[
  {
    "kazanim_kodu": "İBT.1.1",
    "kazanim_metni": "İslam biliminin temel kavramları ve gebeceri ve becerilerin süreç nel özellikleri ile ilgili kaynağı yorumlayabilme",
    "sinif": 11,
    "okul_turu": "ihl",
    "brans_slug": "ihl_meslek_dersleri",
    "ders": "İslam Bilim Tarihi",
    "unite_no": 1,
    "unite_adi": "YENİ BİR MEDENİYETİN",
    "kaynak_pdf": "2026326134623635-islambilimtarh.pdf",
    "kaynak_sayfa": 12,
    "extraction_yontemi": "regex_tipD",
    "confidence": "high"
  },
  {
    "kazanim_kodu": "İBT.2.1",
    "kazanim_metni": "Yeni siyasi, iktisadi, kültürel yapılanma ve ilim merkezlerinin oluşumu ile ilgili kaynağı yorumlayabilme",
    "sinif": 11,
    "okul_turu": "ihl",
    "brans_slug": "ihl_meslek_dersleri",
    "ders": "İslam Bilim Tarihi",
    "unite_no": 1,
    "unite_adi": "İSLAM BİLİMİNDE KURUMSALLAŞMA",
    "kaynak_pdf": "2026326134623635-islambilimtarh.pdf",
    "kaynak_sayfa": 20,
    "extraction_yontemi": "regex_tipD",
    "confidence": "high"
  },
  {
    "kazanim_kodu": "İBT.3.1",
    "kazanim_metni": "Endülüs Bilim Havzası’nda yapılan bilimsel çalışmalar ile ilgili kaynaklardan bilgi toplayabilme",
    "sinif": 11,
    "okul_turu": "ihl",
    "brans_slug": "ihl_meslek_dersleri",
    "ders": "İslam Bilim Tarihi",
    "unite_no": 1,
    "unite_adi": "ENDÜLÜS’TE İSLAM BİLİMİNİN GELİŞİMİ",
    "kaynak_pdf": "2026326134623635-islambilimtarh.pdf",
    "kaynak_sayfa": 26,
    "extraction_yontemi": "regex_tipD",
    "confidence": "high"
  },
  {
    "kazanim_kodu": "İBT.4.1",
    "kazanim_metni": "Türkistan Bilim Havzası’ndaki bilimsel çalışmaları tarihsel bağlamda değerlendirebilme",
    "sinif": 11,
    "okul_turu": "ihl",
    "brans_slug": "ihl_meslek_dersleri",
    "ders": "İslam Bilim Tarihi",
    "unite_no": 1,
    "unite_adi": "DEĞİŞEN DÜNYADA İSLAM BİLİMİ",
    "kaynak_pdf": "2026326134623635-islambilimtarh.pdf",
    "kaynak_sayfa": 30,
    "extraction_yontemi": "regex_tipD",
    "confidence": "high"
  },
  {
    "kazanim_kodu": "İBT.5.1",
    "kazanim_metni": "Erken Dönem Osmanlı bilim anlayışının oluşumunu ve Türkçenin bilim dili hâline gelmesini yorumlayabilme",
    "sinif": 11,
    "okul_turu": "ihl",
    "brans_slug": "ihl_meslek_dersleri",
    "ders": "İslam Bilim Tarihi",
    "unite_no": 1,
    "unite_adi": "OSMANLILARDA BİLİMSEL ÇALIŞMALAR",
    "kaynak_pdf": "2026326134623635-islambilimtarh.pdf",
    "kaynak_sayfa": 34,
    "extraction_yontemi": "regex_tipD",
    "confidence": "high"
  },
  {
    "kazanim_kodu": "İBT.6.1",
    "kazanim_metni": "Cumhuriyet Dönemi bilim politikalarını ve yeni kurulan bilim kurumlarının çalışmalarını yorumlayabilme",
    "sinif": 11,
    "okul_turu": "ihl",
    "brans_slug": "ihl_meslek_dersleri",
    "ders": "İslam Bilim Tarihi",
    "unite_no": 1,
    "unite_adi": "CUMHURİYET DÖNEMİ BİLİMSEL ÇALIŞMALARI",
    "kaynak_pdf": "2026326134623635-islambilimtarh.pdf",
    "kaynak_sayfa": 42,
    "extraction_yontemi": "regex_tipD",
    "confidence": "high"
  },
  {
    "kazanim_kodu": "İBT.1.2",
    "kazanim_metni": "İslam’ın doğduğu ortamın kültürel, ekonomik ve dinî özelliklerini sentezleyebilme",
    "sinif": 11,
    "okul_turu": "ihl",
    "brans_slug": "ihl_meslek_dersleri",
    "ders": "İslam Bilim Tarihi",
    "unite_no": 2,
    "unite_adi": "YENİ BİR MEDENİYETİN DOĞUŞU",
    "kaynak_pdf": "2026326134623635-islambilimtarh.pdf",
    "kaynak_sayfa": 14,
    "extraction_yontemi": "regex_tipD",
    "confidence": "high"
  },
  {
    "kazanim_kodu": "İBT.2.2",
    "kazanim_metni": "İslam dünyasında ilk medreselerin kuruluş nedenlerini sorgulayabilme",
    "sinif": 11,
    "okul_turu": "ihl",
    "brans_slug": "ihl_meslek_dersleri",
    "ders": "İslam Bilim Tarihi",
    "unite_no": 2,
    "unite_adi": "İSLAM BİLİMİNDE KURUMSALLAŞMA",
    "kaynak_pdf": "2026326134623635-islambilimtarh.pdf",
    "kaynak_sayfa": 20,
    "extraction_yontemi": "regex_tipD",
    "confidence": "high"
  },
  {
    "kazanim_kodu": "İBT.3.2",
    "kazanim_metni": "Harita üzerinden İslam biliminin Avrupa’ya geçiş yolları ile ilgili çıkarım yapabilme",
    "sinif": 11,
    "okul_turu": "ihl",
    "brans_slug": "ihl_meslek_dersleri",
    "ders": "İslam Bilim Tarihi",
    "unite_no": 2,
    "unite_adi": "ENDÜLÜS’TE İSLAM BİLİMİNİN GELİŞİMİ",
    "kaynak_pdf": "2026326134623635-islambilimtarh.pdf",
    "kaynak_sayfa": 26,
    "extraction_yontemi": "regex_tipD",
    "confidence": "high"
  },
  {
    "kazanim_kodu": "İBT.4.2",
    "kazanim_metni": "Haçlı saldırılarının bilimin Batı’ya geçişindeki etkilerini yapılandırabilme",
    "sinif": 11,
    "okul_turu": "ihl",
    "brans_slug": "ihl_meslek_dersleri",
    "ders": "İslam Bilim Tarihi",
    "unite_no": 2,
    "unite_adi": "DEĞİŞEN DÜNYADA İSLAM BİLİMİ",
    "kaynak_pdf": "2026326134623635-islambilimtarh.pdf",
    "kaynak_sayfa": 30,
    "extraction_yontemi": "regex_tipD",
    "confidence": "high"
  },
  {
    "kazanim_kodu": "İBT.5.2",
    "kazanim_metni": "İstanbul’un bilim merkezi hâline gelme sürecindeki unsurları yapılandırabilme",
    "sinif": 11,
    "okul_turu": "ihl",
    "brans_slug": "ihl_meslek_dersleri",
    "ders": "İslam Bilim Tarihi",
    "unite_no": 2,
    "unite_adi": "OSMANLILARDA BİLİMSEL ÇALIŞMALAR",
    "kaynak_pdf": "2026326134623635-islambilimtarh.pdf",
    "kaynak_sayfa": 34,
    "extraction_yontemi": "regex_tipD",
    "confidence": "high"
  },
  {
    "kazanim_kodu": "İBT.6.2",
    "kazanim_metni": "Cumhuriyet Dönemi bilim insanlarının çalışmaları hakkında kaynaklardan bilgi toplayabilme",
    "sinif": 11,
    "okul_turu": "ihl",
    "brans_slug": "ihl_meslek_dersleri",
    "ders": "İslam Bilim Tarihi",
    "unite_no": 2,
    "unite_adi": "CUMHURİYET DÖNEMİ BİLİMSEL ÇALIŞMALARI",
    "kaynak_pdf": "2026326134623635-islambilimtarh.pdf",
    "kaynak_sayfa": 42,
    "extraction_yontemi": "regex_tipD",
    "confidence": "high"
  },
  {
    "kazanim_kodu": "İBT.1.3",
    "kazanim_metni": "İslam dünyasında bilimin gelişmesinde etkili olan unsurları yorumlayabilme",
    "sinif": 11,
    "okul_turu": "ihl",
    "brans_slug": "ihl_meslek_dersleri",
    "ders": "İslam Bilim Tarihi",
    "unite_no": 3,
    "unite_adi": "YENİ BİR MEDENİYETİN DOĞUŞU",
    "kaynak_pdf": "2026326134623635-islambilimtarh.pdf",
    "kaynak_sayfa": 14,
    "extraction_yontemi": "regex_tipD",
    "confidence": "high"
  },
  {
    "kazanim_kodu": "İBT.2.3",
    "kazanim_metni": "İslam bilim tarihinde gözlem ve deneye yönelimi tarihsel bağlamsallaştırma ile değerlendirebilme",
    "sinif": 11,
    "okul_turu": "ihl",
    "brans_slug": "ihl_meslek_dersleri",
    "ders": "İslam Bilim Tarihi",
    "unite_no": 3,
    "unite_adi": "İSLAM BİLİMİNDE KURUMSALLAŞMA",
    "kaynak_pdf": "2026326134623635-islambilimtarh.pdf",
    "kaynak_sayfa": 20,
    "extraction_yontemi": "regex_tipD",
    "confidence": "high"
  },
  {
    "kazanim_kodu": "İBT.3.3",
    "kazanim_metni": "İslam biliminin Avrupa’da yeni bir medeniyetin doğuşuna etkisini yorumlayabilme",
    "sinif": 11,
    "okul_turu": "ihl",
    "brans_slug": "ihl_meslek_dersleri",
    "ders": "İslam Bilim Tarihi",
    "unite_no": 3,
    "unite_adi": "ENDÜLÜS’TE İSLAM BİLİMİNİN GELİŞİMİ",
    "kaynak_pdf": "2026326134623635-islambilimtarh.pdf",
    "kaynak_sayfa": 26,
    "extraction_yontemi": "regex_tipD",
    "confidence": "high"
  },
  {
    "kazanim_kodu": "İBT.4.3",
    "kazanim_metni": "Büyük Selçuklular, Birinci Beylikler ve Türkiye Selçukluları Dönemi bilimsel çalışmaları ile ilgili tümevarımsal akıl yürütebilme",
    "sinif": 11,
    "okul_turu": "ihl",
    "brans_slug": "ihl_meslek_dersleri",
    "ders": "İslam Bilim Tarihi",
    "unite_no": 3,
    "unite_adi": "DEĞİŞEN DÜNYADA İSLAM BİLİMİ",
    "kaynak_pdf": "2026326134623635-islambilimtarh.pdf",
    "kaynak_sayfa": 30,
    "extraction_yontemi": "regex_tipD",
    "confidence": "high"
  },
  {
    "kazanim_kodu": "İBT.5.3",
    "kazanim_metni": "Takıyyüddin Rasıd ve İstanbul Rasathanesinin açılışı ve yapılan çalışmalar ile ilgili tartışabilme",
    "sinif": 11,
    "okul_turu": "ihl",
    "brans_slug": "ihl_meslek_dersleri",
    "ders": "İslam Bilim Tarihi",
    "unite_no": 3,
    "unite_adi": "OSMANLILARDA BİLİMSEL ÇALIŞMALAR",
    "kaynak_pdf": "2026326134623635-islambilimtarh.pdf",
    "kaynak_sayfa": 34,
    "extraction_yontemi": "regex_tipD",
    "confidence": "high"
  },
  {
    "kazanim_kodu": "İBT.1.4",
    "kazanim_metni": "Şehirlerin bilim, sanat ve irfana etkisi ile ilgili bilgi toplayabilme",
    "sinif": 11,
    "okul_turu": "ihl",
    "brans_slug": "ihl_meslek_dersleri",
    "ders": "İslam Bilim Tarihi",
    "unite_no": 4,
    "unite_adi": "YENİ BİR MEDENİYETİN DOĞUŞU",
    "kaynak_pdf": "2026326134623635-islambilimtarh.pdf",
    "kaynak_sayfa": 14,
    "extraction_yontemi": "regex_tipD",
    "confidence": "high"
  },
  {
    "kazanim_kodu": "İBT.2.4",
    "kazanim_metni": "İslam dünyasında gök bilimi, matematik, fen, sağlık bilimleri ve sosyal bilimler alanında yapılan çalışmaları yorumlayabilme",
    "sinif": 11,
    "okul_turu": "ihl",
    "brans_slug": "ihl_meslek_dersleri",
    "ders": "İslam Bilim Tarihi",
    "unite_no": 4,
    "unite_adi": "İSLAM BİLİMİNDE KURUMSALLAŞMA",
    "kaynak_pdf": "2026326134623635-islambilimtarh.pdf",
    "kaynak_sayfa": 20,
    "extraction_yontemi": "regex_tipD",
    "confidence": "high"
  },
  {
    "kazanim_kodu": "İBT.5.4",
    "kazanim_metni": "Osmanlı Devleti’nde coğrafya, haritacılık, kartografya ve tıp alanında yapılan çalışmaları kaynaklardan inceleyebilme",
    "sinif": 11,
    "okul_turu": "ihl",
    "brans_slug": "ihl_meslek_dersleri",
    "ders": "İslam Bilim Tarihi",
    "unite_no": 4,
    "unite_adi": "OSMANLILARDA BİLİMSEL ÇALIŞMALAR",
    "kaynak_pdf": "2026326134623635-islambilimtarh.pdf",
    "kaynak_sayfa": 34,
    "extraction_yontemi": "regex_tipD",
    "confidence": "high"
  },
  {
    "kazanim_kodu": "İBT.1.5",
    "kazanim_metni": "İslami ilimlerin oluşumunu kaynağından inceleyebilme",
    "sinif": 11,
    "okul_turu": "ihl",
    "brans_slug": "ihl_meslek_dersleri",
    "ders": "İslam Bilim Tarihi",
    "unite_no": 5,
    "unite_adi": "YENİ BİR MEDENİYETİN DOĞUŞU",
    "kaynak_pdf": "2026326134623635-islambilimtarh.pdf",
    "kaynak_sayfa": 14,
    "extraction_yontemi": "regex_tipD",
    "confidence": "high"
  },
  {
    "kazanim_kodu": "İBT.2.5",
    "kazanim_metni": "İslam dünyasında yapılan teknik ürünlerle ilgili analojik akıl yürütebilme",
    "sinif": 11,
    "okul_turu": "ihl",
    "brans_slug": "ihl_meslek_dersleri",
    "ders": "İslam Bilim Tarihi",
    "unite_no": 5,
    "unite_adi": "İSLAM BİLİMİNDE KURUMSALLAŞMA",
    "kaynak_pdf": "2026326134623635-islambilimtarh.pdf",
    "kaynak_sayfa": 20,
    "extraction_yontemi": "regex_tipD",
    "confidence": "high"
  },
  {
    "kazanim_kodu": "İBT.5.5",
    "kazanim_metni": "Osmanlı Devleti’nde yeni eğitim kurumlarının açılış nedenlerini ve yeni bilimsel anlayışı sorgulayabilme",
    "sinif": 11,
    "okul_turu": "ihl",
    "brans_slug": "ihl_meslek_dersleri",
    "ders": "İslam Bilim Tarihi",
    "unite_no": 5,
    "unite_adi": "OSMANLILARDA BİLİMSEL ÇALIŞMALAR",
    "kaynak_pdf": "2026326134623635-islambilimtarh.pdf",
    "kaynak_sayfa": 34,
    "extraction_yontemi": "regex_tipD",
    "confidence": "high"
  },
  {
    "kazanim_kodu": "İBT.1.6",
    "kazanim_metni": "Teoriden pratiğe İslam dünyasında bilime yönelik ilk çalışma alanları ile ilgili çıkarım yapabilme",
    "sinif": 11,
    "okul_turu": "ihl",
    "brans_slug": "ihl_meslek_dersleri",
    "ders": "İslam Bilim Tarihi",
    "unite_no": 6,
    "unite_adi": "YENİ BİR MEDENİYETİN DOĞUŞU",
    "kaynak_pdf": "2026326134623635-islambilimtarh.pdf",
    "kaynak_sayfa": 14,
    "extraction_yontemi": "regex_tipD",
    "confidence": "high"
  },
  {
    "kazanim_kodu": "İBT.5.6",
    "kazanim_metni": "XVIII-XIX. yüzyılda eğitim ve bilim alanında faaliyet gösteren bilim insanlarının çalışmaları hakkında kaynaklardan bilgi toplayabilme",
    "sinif": 11,
    "okul_turu": "ihl",
    "brans_slug": "ihl_meslek_dersleri",
    "ders": "İslam Bilim Tarihi",
    "unite_no": 6,
    "unite_adi": "OSMANLILARDA BİLİMSEL ÇALIŞMALAR",
    "kaynak_pdf": "2026326134623635-islambilimtarh.pdf",
    "kaynak_sayfa": 35,
    "extraction_yontemi": "regex_tipD",
    "confidence": "high"
  },
  {
    "kazanim_kodu": "İBT.1.7",
    "kazanim_metni": "İslam dünyasında tercüme faaliyetlerinin nedenlerini sorgulayabilme",
    "sinif": 11,
    "okul_turu": "ihl",
    "brans_slug": "ihl_meslek_dersleri",
    "ders": "İslam Bilim Tarihi",
    "unite_no": 7,
    "unite_adi": "YENİ BİR MEDENİYETİN DOĞUŞU",
    "kaynak_pdf": "2026326134623635-islambilimtarh.pdf",
    "kaynak_sayfa": 15,
    "extraction_yontemi": "regex_tipD",
    "confidence": "high"
  },
  {
    "kazanim_kodu": "İBT.5.7",
    "kazanim_metni": "Osmanlı Devleti’nde modern yapılanmanın ve Rasathâne-i Âmire’de yapılan çalışmaların günümüze etkilerini değerlendirebilme",
    "sinif": 11,
    "okul_turu": "ihl",
    "brans_slug": "ihl_meslek_dersleri",
    "ders": "İslam Bilim Tarihi",
    "unite_no": 7,
    "unite_adi": "OSMANLILARDA BİLİMSEL ÇALIŞMALAR",
    "kaynak_pdf": "2026326134623635-islambilimtarh.pdf",
    "kaynak_sayfa": 35,
    "extraction_yontemi": "regex_tipD",
    "confidence": "high"
  },
  {
    "kazanim_kodu": "İBT.1.8",
    "kazanim_metni": "Bilim alanlarını yeniden sınıflandırabilme",
    "sinif": 11,
    "okul_turu": "ihl",
    "brans_slug": "ihl_meslek_dersleri",
    "ders": "İslam Bilim Tarihi",
    "unite_no": 8,
    "unite_adi": "YENİ BİR MEDENİYETİN DOĞUŞU",
    "kaynak_pdf": "2026326134623635-islambilimtarh.pdf",
    "kaynak_sayfa": 15,
    "extraction_yontemi": "regex_tipD",
    "confidence": "high"
  }
]